atro_core/__init__.py
atro_core/utils/atro_dict.py
atro_core-0.0.1.dist-info/LICENSE
atro_core-0.0.1.dist-info/METADATA
atro_core-0.0.1.dist-info/WHEEL
atro_core-0.0.1.dist-info/RECORD
